jquery.py
PyjQuery-3.5.1.1.data/scripts/jquery.py
PyjQuery-3.5.1.1.dist-info/LICENSE.txt
PyjQuery-3.5.1.1.dist-info/METADATA
PyjQuery-3.5.1.1.dist-info/WHEEL
PyjQuery-3.5.1.1.dist-info/top_level.txt
PyjQuery-3.5.1.1.dist-info/RECORD
